asyncpal/__init__.py
asyncpal/__main__.py
asyncpal/errors/__init__.py
asyncpal/future/__init__.py
asyncpal/misc/__init__.py
asyncpal/pool/__init__.py
asyncpal/pool/processpool.py
asyncpal/pool/threadpool.py
asyncpal/worker/__init__.py
asyncpal/worker/processworker.py
asyncpal/worker/threadworker.py
tests/__init__.py
tests/__main__.py
tests/funcs.py
tests/test_future.py
tests/test_imports.py
tests/test_misc.py
tests/test_processpool.py
tests/test_threadpool.py
asyncpal-0.0.7.dist-info/LICENSE
asyncpal-0.0.7.dist-info/METADATA
asyncpal-0.0.7.dist-info/WHEEL
asyncpal-0.0.7.dist-info/entry_points.txt
asyncpal-0.0.7.dist-info/top_level.txt
asyncpal-0.0.7.dist-info/RECORD
